HashableDict/HashableDict.py
HashableDict/__init__.py
HashableDict-0.3.0.dist-info/LICENSE.md
HashableDict-0.3.0.dist-info/METADATA
HashableDict-0.3.0.dist-info/WHEEL
HashableDict-0.3.0.dist-info/top_level.txt
HashableDict-0.3.0.dist-info/RECORD
