Metadata-Version: 2.1
Name: HashableDict
Version: 0.3.0
Summary: A hashable immutable dictionary
Home-page: https://github.com/IFcoltransG/HashableDict
Author: IFcoltransG
Author-email: IFcoltransG+PyPI@protonmail.ch
License: unlicense
Download-URL: https://github.com/IFcoltransG/HashableDict/archive/v0.3.0.tar.gz
Keywords: dictionary,dict,frozen,hashable,immutable
Platform: UNKNOWN
Classifier: Programming Language :: Python :: 3
Classifier: License :: Public Domain
Classifier: Operating System :: OS Independent
Classifier: Topic :: Utilities
Requires-Python: >=3.7
